hdl/rtl/top.sv
module top (
    input logic clk,
    input logic rst,
    output logic [3:0] data_out
);
    always_ff @(posedge clk or posedge rst) begin
        if (rst)
            data_out <= 4'b0000;
        else
            data_out <= data_out + 1;
    end
endmodule

sim/tb/tb_top.sv
module tb_top;
    logic clk;
    logic rst;
    logic [3:0] data_out;

    // Instantiate DUT
    top uut (
        .clk(clk),
        .rst(rst),
        .data_out(data_out)
    );

    // Clock Generation
    initial begin
        clk = 0;
        forever #5 clk = ~clk; // 10ns clock period
    end

    // Stimulus
    initial begin
        rst = 1; #10;
        rst = 0; #100;
        $finish;
    end

    // Dump Waveform
    initial begin
        $dumpfile("../../sim/waves/tb_top.vcd");
        $dumpvars(0, tb_top);
    end
endmodule

sim/waves/tb_top.vcd
$date
	Sat Dec  7 22:13:54 2024
$end
$version
	Icarus Verilog
$end
$timescale
	1s
$end
$scope module tb_top $end
$var wire 4 ! data_out [3:0] $end
$var reg 1 " clk $end
$var reg 1 # rst $end
$scope module uut $end
$var wire 1 " clk $end
$var wire 1 # rst $end
$var reg 4 $ data_out [3:0] $end
$upscope $end
$upscope $end
$enddefinitions $end
$comment Show the parameter values. $end
$dumpall
$end
#0
$dumpvars
b0 $
1#
0"
b0 !
$end
#5
1"
#10
0"
0#
#15
b1 !
b1 $
1"
#20
0"
#25
b10 !
b10 $
1"
#30
0"
#35
b11 !
b11 $
1"
#40
0"
#45
b100 !
b100 $
1"
#50
0"
#55
b101 !
b101 $
1"
#60
0"
#65
b110 !
b110 $
1"
#70
0"
#75
b111 !
b111 $
1"
#80
0"
#85
b1000 !
b1000 $
1"
#90
0"
#95
b1001 !
b1001 $
1"
#100
0"
#105
b1010 !
b1010 $
1"
